cssUnicodeRange/__init__.py
cssUnicodeRange/cmdline.py
cssUnicodeRange-1.0.0.dist-info/LICENSE
cssUnicodeRange-1.0.0.dist-info/METADATA
cssUnicodeRange-1.0.0.dist-info/WHEEL
cssUnicodeRange-1.0.0.dist-info/entry_points.txt
cssUnicodeRange-1.0.0.dist-info/top_level.txt
cssUnicodeRange-1.0.0.dist-info/zip-safe
cssUnicodeRange-1.0.0.dist-info/RECORD
