Metadata-Version: 2.1
Name: cssUnicodeRange
Version: 1.0.0
Summary: Generate the unicode-range CSS property for a webfont file.
Home-page: https://www.lucasfonts.com/
Author: Jens Kutilek
Project-URL: Bug Tracker, https://github.com/LucasFonts/css-unicode-range/issues
Project-URL: Source Code, https://github.com/LucasFonts/css-unicode-range
Classifier: Programming Language :: Python :: 3
Classifier: Operating System :: OS Independent
Classifier: Environment :: Console
Requires-Python: >=3.9
License-File: LICENSE
Requires-Dist: fonttools[woff]
